MANIFEST.in
README.rst
setup.cfg
setup.py
test_requires.txt
JsonWeb.egg-info/PKG-INFO
JsonWeb.egg-info/SOURCES.txt
JsonWeb.egg-info/dependency_links.txt
JsonWeb.egg-info/entry_points.txt
JsonWeb.egg-info/not-zip-safe
JsonWeb.egg-info/top_level.txt
jsonweb/__init__.py
jsonweb/_local.py
jsonweb/decode.py
jsonweb/encode.py
jsonweb/exceptions.py
jsonweb/py3k.py
jsonweb/schema.py
jsonweb/validators.py
jsonweb/tests/__init__.py
jsonweb/tests/test_decode.py
jsonweb/tests/test_decode_schema.py
jsonweb/tests/test_encode.py
jsonweb/tests/test_local.py
jsonweb/tests/test_py3k.py
jsonweb/tests/test_schema.py
jsonweb/tests/test_validators.py